catfile/__init__.py
catfile/main.py
catfile-1.0.2.dist-info/METADATA
catfile-1.0.2.dist-info/WHEEL
catfile-1.0.2.dist-info/entry_points.txt
catfile-1.0.2.dist-info/top_level.txt
catfile-1.0.2.dist-info/RECORD
