Metadata-Version: 2.4
Name: catfile
Version: 1.0.2
Summary: A simple Python CLI tool to automatically sort files into directories by type
Author: Johann
Author-email: Jonathan <reinishimiya22@gmail.com>
License: MIT
Requires-Python: >=3.8
Dynamic: author
